{"readme.md":"CbDexvCf","note_c___make.md":"BuhROttD","note_deep learning_vision transformer.md":"BRf1jY16","note_network_数据链路层.md":"DHEKj7rj","note_network_网际层.md":"BzH47JF1","note_network_物理层.md":"CddQmtsI","note_notes_git.md":"Cudtb_9-","note_notes_linux.md":"nBxSPkus","note_notes_dorker.md":"CYOSIDoc","note_data structure and algorithms_哈希表.md":"D2vt11mi","note_软考_第三章数据结构.md":"FzNrMgDE","note_notes_vitepress.md":"CP-STgCK","note_network_传输层.md":"CNO-XvjF","note_c___动态库与静态库.md":"BasNT63G","note_network_基础概念和体系结构.md":"YkqhfzOB","note_c___并发编程.md":"Drs9-SdD","index.md":"BjUBB_tG","note_network_应用层.md":"pJp6lOxc","note_c___gdb.md":"C6CvdmkW","note_c___stl.md":"DYEEzBXu","note_软考_第一章计算机系统知识.md":"CGBJA7yY","note_deep learning_分类网络.md":"DU0BUr_K","note_deep learning_rcnn系列.md":"wKWUmQcn","note_deep learning_误差计算与反向传播.md":"Bba87TxB","note_deep learning_mmdetection.md":"DqC6qnz8","note_软考_第二章程序设计语言设计.md":"BfgL0YtH","note_c___c__.md":"D8qXmCB5"}
